dataframe_decorators/__init__.py
dataframe_decorators/feature.py
dataframe_decorators/join.py
dataframe_decorators/pipe.py
dataframe_decorators/utils.py
dataframe_decorators-0.2.0.dist-info/METADATA
dataframe_decorators-0.2.0.dist-info/WHEEL
dataframe_decorators-0.2.0.dist-info/RECORD
