Metadata-Version: 2.1
Name: dataframe-decorators
Version: 0.2.0
Summary: Decorators for pipeline functions involving dataframes
Author: Patrick Bray
Requires-Python: >=3.10,<4.0
Classifier: Programming Language :: Python :: 3
Classifier: Programming Language :: Python :: 3.10
Classifier: Programming Language :: Python :: 3.11
Requires-Dist: loguru (>=0.7.0,<0.8.0)
